odyssey_omniversemcp/__init__.py
odyssey_omniversemcp/server.py
odyssey_omniversemcp-0.4.0.dist-info/METADATA
odyssey_omniversemcp-0.4.0.dist-info/WHEEL
odyssey_omniversemcp-0.4.0.dist-info/entry_points.txt
odyssey_omniversemcp-0.4.0.dist-info/RECORD
