Metadata-Version: 2.4
Name: odyssey-omniversemcp
Version: 0.4.0
Summary: Add your description here
Requires-Python: >=3.13
Requires-Dist: mcp[cli]>=1.9.4
